tests/__init__.py
tests/test_cleanup_requirements.py
tests/test_requirements.py
toxbat/__init__.py
toxbat/requirements.py
tox_battery-0.6.2.dist-info/LICENSE
tox_battery-0.6.2.dist-info/METADATA
tox_battery-0.6.2.dist-info/WHEEL
tox_battery-0.6.2.dist-info/entry_points.txt
tox_battery-0.6.2.dist-info/top_level.txt
tox_battery-0.6.2.dist-info/RECORD
