Metadata-Version: 2.1
Name: tox-battery
Version: 0.6.2
Summary: Additional functionality for tox
Home-page: https://github.com/signalpillar/tox-battery
Author: Volodymyr Vitvitskyi
Author-email: contact.volodymyr@gmail.com
License: http://opensource.org/licenses/MIT
Classifier: Development Status :: 5 - Production/Stable
Classifier: Intended Audience :: Developers
Classifier: Operating System :: POSIX
Classifier: Operating System :: Microsoft :: Windows
Classifier: Operating System :: MacOS :: MacOS X
Classifier: Topic :: Software Development :: Testing
Classifier: Topic :: Software Development :: Libraries
Classifier: Programming Language :: Python :: 3
License-File: LICENSE
Requires-Dist: tox (<4)
